nwc_pattern_miner/__init__.py
nwc_pattern_miner/module/__init__.py
nwc_pattern_miner/module/pattern_mining_client.py
nwc_pattern_miner/module/patternminer.py
nwc_pattern_miner/module/utilities.py
nwc_pattern_miner/module/mining/__init__.py
nwc_pattern_miner/module/mining/candidatepattern.py
nwc_pattern_miner/module/mining/latticegraph.py
nwc_pattern_miner/module/mining/latticenode.py
nwc_pattern_miner/module/patterncount/__init__.py
nwc_pattern_miner/module/patterncount/count_strategy.py
nwc_pattern_miner/module/patterncount/stategraph.py
nwc_pattern_miner/module/pruning/__init__.py
nwc_pattern_miner/module/pruning/pruning_strategy.py
nwc_pattern_miner/module/pruning/support_pruning.py
nwc_pattern_miner/module/pruning/ub_pruning.py
nwc_pattern_miner-0.2.dist-info/LICENSE
nwc_pattern_miner-0.2.dist-info/METADATA
nwc_pattern_miner-0.2.dist-info/WHEEL
nwc_pattern_miner-0.2.dist-info/top_level.txt
nwc_pattern_miner-0.2.dist-info/RECORD
