Metadata-Version: 2.1
Name: nwc-pattern-miner
Version: 0.2
Summary: Mines sequence patterns co-occuring with non-compliant windows in a target feature.
Home-page: https://github.com/SpatialUMN/nwc-pattern-mining
Author: Anirudh Agarwal
Author-email: agarw228@umn.edu
License: UNKNOWN
Platform: UNKNOWN
Classifier: Programming Language :: Python :: 3
Classifier: License :: OSI Approved :: MIT License
Classifier: Operating System :: OS Independent
Requires-Python: >=3.7
Requires-Dist: pandas (==1.2.4)
Requires-Dist: tqdm (==4.60.0)
